{
  "project_info": {
    "project_number": "741583862119",
    "project_id": "job-alley-3f825",
    "storage_bucket": "job-alley-3f825.appspot.com"
  },
  "client": [
    {
      "client_info": {
        "mobilesdk_app_id": "1:741583862119:android:32a20a43e17811d9da17c2",
        "android_client_info": {
          "package_name": "com.example.joballey"
        }
      },
      "oauth_client": [
        {
          "client_id": "741583862119-1i1ev9ekugq5b32qhp8u7hnh3rm97ec2.apps.googleusercontent.com",
          "client_type": 3
        }
      ],
      "api_key": [
        {
          "current_key": "AIzaSyCkIrmLGGougR5vJCt8DLfRaRb2wYn4Fdo"
        }
      ],
      "services": {
        "appinvite_service": {
          "other_platform_oauth_client": [
            {
              "client_id": "741583862119-1i1ev9ekugq5b32qhp8u7hnh3rm97ec2.apps.googleusercontent.com",
              "client_type": 3
            }
          ]
        }
      }
    }
  ],
  "configuration_version": "1"
}